s3s3/__init__.py
s3s3/api.py
s3s3/client.py
s3s3/config.py
s3s3/log.py
s3s3/version.py
s3s3/pubsub/__init__.py
s3s3/pubsub/redis.py
s3s3/scripts/__init__.py
s3s3/scripts/bucket.py
s3s3/scripts/echo_s3s3_ini_template.py
s3s3/scripts/echo_s3s3_supervisord_conf.py
s3s3/scripts/listen.py
s3s3-0.1.10.data/data/extras/s3s3.conf
s3s3-0.1.10.data/data/extras/s3s3.ini.dist
s3s3-0.1.10.dist-info/DESCRIPTION.rst
s3s3-0.1.10.dist-info/entry_points.txt
s3s3-0.1.10.dist-info/METADATA
s3s3-0.1.10.dist-info/metadata.json
s3s3-0.1.10.dist-info/RECORD
s3s3-0.1.10.dist-info/top_level.txt
s3s3-0.1.10.dist-info/WHEEL
