Metadata-Version: 2.0
Name: s3s3
Version: 0.1.10
Summary: A microservice to move files from S3 APIs (Swift or Ceph) to other S3 APIs.
Home-page: https://github.com/lsst-sqre/s3s3
Author: jmatt
Author-email: jmatt@lsst.org
License: UNKNOWN
Platform: UNKNOWN
Classifier: Development Status :: 4 - Beta
Classifier: Intended Audience :: Developers
Classifier: Intended Audience :: Information Technology
Classifier: License :: OSI Approved :: MIT License
Classifier: Operating System :: OS Independent
Classifier: Programming Language :: Python :: 3.4
Classifier: Programming Language :: Python :: 3.5
Classifier: Topic :: Software Development :: Libraries
Classifier: Topic :: System
Classifier: Topic :: System :: Archiving :: Backup
Classifier: Topic :: System :: Systems Administration
Requires-Dist: boto (==2.38.0)
Requires-Dist: redis (==2.10.3)
